collectd_rabbitmq/__init__.py
collectd_rabbitmq/collectd_plugin.py
collectd_rabbitmq/rabbit.py
collectd_rabbitmq/utils.py
collectd_rabbitmq-1.20.0.data/data/share/collectd-rabbitmq/types.db.custom
collectd_rabbitmq-1.20.0.dist-info/METADATA
collectd_rabbitmq-1.20.0.dist-info/RECORD
collectd_rabbitmq-1.20.0.dist-info/WHEEL
collectd_rabbitmq-1.20.0.dist-info/top_level.txt
