Metadata-Version: 2.1
Name: collectd-rabbitmq
Version: 1.20.0
Summary: A collected plugin, written in python, tocollect statistics from RabbitMQ.
Home-page: https://github.com/NYTimes/collectd-rabbitmq
Author: Mike Buzzetti
Author-email: mike.buzzetti@gmail.com
License: Apache
Keywords: collectd-rabbitmq
Platform: UNKNOWN
Classifier: Development Status :: 2 - Pre-Alpha
Classifier: Intended Audience :: Developers
Classifier: License :: OSI Approved :: Apache Software License
Classifier: Natural Language :: English
Classifier: Programming Language :: Python :: 2
Classifier: Programming Language :: Python :: 2.7
